tornado_db/__init__.py
tornado_db-0.0.1.dist-info/LICENSE
tornado_db-0.0.1.dist-info/METADATA
tornado_db-0.0.1.dist-info/WHEEL
tornado_db-0.0.1.dist-info/top_level.txt
tornado_db-0.0.1.dist-info/RECORD
